dep_reader/__init__.py
dep_reader/__main__.py
dep_reader/args/Args.py
dep_reader/args/__init__.py
dep_reader/output/Output.py
dep_reader/output/__init__.py
dep_reader/reader/Reader.py
dep_reader/reader/__init__.py
dep_reader/util/Util.py
dep_reader/util/__init__.py
dep_reader-1.0.0.dist-info/METADATA
dep_reader-1.0.0.dist-info/WHEEL
dep_reader-1.0.0.dist-info/entry_points.txt
dep_reader-1.0.0.dist-info/top_level.txt
dep_reader-1.0.0.dist-info/RECORD
