Metadata-Version: 2.1
Name: dep_reader
Version: 1.0.0
Summary: Read Data Exfiltration Protocol (DEP) Bytes
Home-page: https://github.com/npdep/dep-reader
Author: npdep
Classifier: Operating System :: OS Independent 
Classifier: Programming Language :: Python :: 3 
Requires-Dist: dep-common
